Metadata-Version: 2.1
Name: textify-docs
Version: 1.0.1
Summary: A package to convert various document types to plain text.
Home-page: https://github.com/BlcMed
Author: Mohamed Boulaich
Author-email: boulaich.mohamed970@gmail.com
License: UNKNOWN
Platform: UNKNOWN
Classifier: Programming Language :: Python :: 3
Classifier: License :: OSI Approved :: GNU General Public License v3 (GPLv3)
Requires-Python: >=3.6
License-File: LICENSE
Requires-Dist: Jinja2==3.1.4
Requires-Dist: MarkupSafe==2.1.5
Requires-Dist: PyYAML==6.0.2
Requires-Dist: certifi==2024.7.4
Requires-Dist: charset-normalizer==3.3.2
Requires-Dist: et-xmlfile==1.1.0
Requires-Dist: filelock==3.15.4
Requires-Dist: fsspec==2024.6.1
Requires-Dist: huggingface-hub==0.24.5
Requires-Dist: idna==3.7
Requires-Dist: lxml==5.3.0
Requires-Dist: mpmath==1.3.0
Requires-Dist: networkx==3.3
Requires-Dist: numpy==2.0.1
Requires-Dist: nvidia-cublas-cu12==12.1.3.1
Requires-Dist: nvidia-cuda-cupti-cu12==12.1.105
Requires-Dist: nvidia-cuda-nvrtc-cu12==12.1.105
Requires-Dist: nvidia-cuda-runtime-cu12==12.1.105
Requires-Dist: nvidia-cudnn-cu12==9.1.0.70
Requires-Dist: nvidia-cufft-cu12==11.0.2.54
Requires-Dist: nvidia-curand-cu12==10.3.2.106
Requires-Dist: nvidia-cusolver-cu12==11.4.5.107
Requires-Dist: nvidia-cusparse-cu12==12.1.0.106
Requires-Dist: nvidia-nccl-cu12==2.20.5
Requires-Dist: nvidia-nvjitlink-cu12==12.6.20
Requires-Dist: nvidia-nvtx-cu12==12.1.105
Requires-Dist: opencv-python==4.10.0.84
Requires-Dist: openpyxl==3.1.5
Requires-Dist: packaging==24.1
Requires-Dist: pandas==2.2.2
Requires-Dist: pdf2image==1.17.0
Requires-Dist: pillow==10.4.0
Requires-Dist: pytesseract==0.3.10
Requires-Dist: python-dateutil==2.9.0.post0
Requires-Dist: python-docx==1.1.2
Requires-Dist: pytz==2024.1
Requires-Dist: requests==2.32.3
Requires-Dist: safetensors==0.4.4
Requires-Dist: six==1.16.0
Requires-Dist: sympy==1.13.2
Requires-Dist: timm==1.0.8
Requires-Dist: tokenizers==0.19.1
Requires-Dist: torch==2.4.0
Requires-Dist: torchvision==0.19.0
Requires-Dist: tqdm==4.66.5
Requires-Dist: transformers==4.44.0
Requires-Dist: triton==3.0.0
Requires-Dist: typing-extensions==4.12.2
Requires-Dist: tzdata==2024.1
Requires-Dist: urllib3==2.2.2
Provides-Extra: dev
Requires-Dist: pytest; extra == "dev"
